LICENSE
MANIFEST.in
README.md
pyproject.toml
setup.cfg
setup.py
wagtail_word/__init__.py
wagtail_word/apps.py
wagtail_word/forms.py
wagtail_word/models.py
wagtail_word/tests.py
wagtail_word.egg-info/PKG-INFO
wagtail_word.egg-info/SOURCES.txt
wagtail_word.egg-info/dependency_links.txt
wagtail_word.egg-info/requires.txt
wagtail_word.egg-info/top_level.txt
wagtail_word/migrations/0001_initial.py
wagtail_word/migrations/0002_worddocumentpage_content.py
wagtail_word/migrations/0003_alter_worddocumentpage_content.py
wagtail_word/migrations/0004_worddocumentembed_worddocumentimage.py
wagtail_word/migrations/0005_delete_worddocumentembed_delete_worddocumentimage.py
wagtail_word/migrations/__init__.py
wagtail_word/migrations/__pycache__/0001_initial.cpython-311.pyc
wagtail_word/migrations/__pycache__/0002_worddocumentpage_content.cpython-311.pyc
wagtail_word/migrations/__pycache__/0003_alter_worddocumentpage_content.cpython-311.pyc
wagtail_word/migrations/__pycache__/0004_worddocumentembed_worddocumentimage.cpython-311.pyc
wagtail_word/migrations/__pycache__/0005_delete_worddocumentembed_delete_worddocumentimage.cpython-311.pyc
wagtail_word/migrations/__pycache__/__init__.cpython-311.pyc
wagtail_word/static/wagtail_word/css/wagtail_word.css
wagtail_word/templates/wagtail_word/page.html